{
  "host": "cpu70",
  "dtype": "float32",
  "seq_len": 2048,
  "batch": 2,
  "vocab_size": 151936,
  "hidden": 1024,
  "embed_param_bytes": 622329856,
  "tail_param_bytes": 622333952,
  "layers": [
    {
      "index": 0,
      "param_bytes": 62923776,
      "activation_bytes_per_sample": 8388608,
      "forward_time_s": 0.3483523095055716,
      "backward_time_s": 0.7579431795020355
    },
    {
      "index": 1,
      "param_bytes": 62923776,
      "activation_bytes_per_sample": 8388608,
      "forward_time_s": 0.3607827134983381,
      "backward_time_s": 0.7665476990077877
    },
    {
      "index": 2,
      "param_bytes": 62923776,
      "activation_bytes_per_sample": 8388608,
      "forward_time_s": 0.37264137050078716,
      "backward_time_s": 0.7606548710173229
    },
    {
      "index": 3,
      "param_bytes": 62923776,
      "activation_bytes_per_sample": 8388608,
      "forward_time_s": 0.37855673702142667,
      "backward_time_s": 0.7387772249785485
    },
    {
      "index": 4,
      "param_bytes": 62923776,
      "activation_bytes_per_sample": 8388608,
      "forward_time_s": 0.3651318329939386,
      "backward_time_s": 0.729114601490437
    },
    {
      "index": 5,
      "param_bytes": 62923776,
      "activation_bytes_per_sample": 8388608,
      "forward_time_s": 0.3070393030066043,
      "backward_time_s": 0.7533220659970539
    },
    {
      "index": 6,
      "param_bytes": 62923776,
      "activation_bytes_per_sample": 8388608,
      "forward_time_s": 0.3540884975082008,
      "backward_time_s": 0.7464869194955099
    },
    {
      "index": 7,
      "param_bytes": 62923776,
      "activation_bytes_per_sample": 8388608,
      "forward_time_s": 0.2880693660117686,
      "backward_time_s": 0.7237167780112941
    },
    {
      "index": 8,
      "param_bytes": 62923776,
      "activation_bytes_per_sample": 8388608,
      "forward_time_s": 0.2857566855091136,
      "backward_time_s": 0.7290429200220387
    },
    {
      "index": 9,
      "param_bytes": 62923776,
      "activation_bytes_per_sample": 8388608,
      "forward_time_s": 0.29027772750123404,
      "backward_time_s": 0.7106151394982589
    },
    {
      "index": 10,
      "param_bytes": 62923776,
      "activation_bytes_per_sample": 8388608,
      "forward_time_s": 0.2797400534909684,
      "backward_time_s": 0.7155376840091776
    },
    {
      "index": 11,
      "param_bytes": 62923776,
      "activation_bytes_per_sample": 8388608,
      "forward_time_s": 0.2792798765003681,
      "backward_time_s": 0.7143702034954913
    },
    {
      "index": 12,
      "param_bytes": 62923776,
      "activation_bytes_per_sample": 8388608,
      "forward_time_s": 0.2848071000044001,
      "backward_time_s": 0.6686549580044812
    },
    {
      "index": 13,
      "param_bytes": 62923776,
      "activation_bytes_per_sample": 8388608,
      "forward_time_s": 0.28286202751041856,
      "backward_time_s": 0.666264676488936
    },
    {
      "index": 14,
      "param_bytes": 62923776,
      "activation_bytes_per_sample": 8388608,
      "forward_time_s": 0.2811258644942427,
      "backward_time_s": 0.6452719344961224
    },
    {
      "index": 15,
      "param_bytes": 62923776,
      "activation_bytes_per_sample": 8388608,
      "forward_time_s": 0.2799432815081673,
      "backward_time_s": 0.6340706049813889
    },
    {
      "index": 16,
      "param_bytes": 62923776,
      "activation_bytes_per_sample": 8388608,
      "forward_time_s": 0.28212958748918027,
      "backward_time_s": 0.6388031484966632
    },
    {
      "index": 17,
      "param_bytes": 62923776,
      "activation_bytes_per_sample": 8388608,
      "forward_time_s": 0.2810177505016327,
      "backward_time_s": 0.6481579410028644
    },
    {
      "index": 18,
      "param_bytes": 62923776,
      "activation_bytes_per_sample": 8388608,
      "forward_time_s": 0.28646478400332853,
      "backward_time_s": 0.6147058524948079
    },
    {
      "index": 19,
      "param_bytes": 62923776,
      "activation_bytes_per_sample": 8388608,
      "forward_time_s": 0.29341683549864683,
      "backward_time_s": 0.6191745704854839
    },
    {
      "index": 20,
      "param_bytes": 62923776,
      "activation_bytes_per_sample": 8388608,
      "forward_time_s": 0.2856272520002676,
      "backward_time_s": 0.6529109445109498
    },
    {
      "index": 21,
      "param_bytes": 62923776,
      "activation_bytes_per_sample": 8388608,
      "forward_time_s": 0.28347371000563726,
      "backward_time_s": 0.6524064495024504
    },
    {
      "index": 22,
      "param_bytes": 62923776,
      "activation_bytes_per_sample": 8388608,
      "forward_time_s": 0.2822223760013003,
      "backward_time_s": 0.6607314970024163
    },
    {
      "index": 23,
      "param_bytes": 62923776,
      "activation_bytes_per_sample": 8388608,
      "forward_time_s": 0.28267463999509346,
      "backward_time_s": 0.6545256079989485
    },
    {
      "index": 24,
      "param_bytes": 62923776,
      "activation_bytes_per_sample": 8388608,
      "forward_time_s": 0.279676644000574,
      "backward_time_s": 0.6220276769890916
    },
    {
      "index": 25,
      "param_bytes": 62923776,
      "activation_bytes_per_sample": 8388608,
      "forward_time_s": 0.28109297149057966,
      "backward_time_s": 0.5793830589827849
    },
    {
      "index": 26,
      "param_bytes": 62923776,
      "activation_bytes_per_sample": 8388608,
      "forward_time_s": 0.28056182351429015,
      "backward_time_s": 0.5794258469977649
    },
    {
      "index": 27,
      "param_bytes": 62923776,
      "activation_bytes_per_sample": 8388608,
      "forward_time_s": 0.27788756699010264,
      "backward_time_s": 0.6056257800082676
    }
  ]
}