{
  "host": "CPU30",
  "dtype": "float32",
  "seq_len": 256,
  "batch": 1,
  "vocab_size": 30522,
  "hidden": 768,
  "embed_param_bytes": 93763584,
  "tail_param_bytes": 0,
  "layers": [
    {
      "index": 0,
      "param_bytes": 28351488,
      "activation_bytes_per_sample": 786432,
      "forward_time_s": 0.013089989020954818,
      "backward_time_s": 0.037366893273429014
    },
    {
      "index": 1,
      "param_bytes": 28351488,
      "activation_bytes_per_sample": 786432,
      "forward_time_s": 0.01874181375023909,
      "backward_time_s": 0.03708257473772392
    },
    {
      "index": 2,
      "param_bytes": 28351488,
      "activation_bytes_per_sample": 786432,
      "forward_time_s": 0.012612638995051384,
      "backward_time_s": 0.05725649726809934
    },
    {
      "index": 3,
      "param_bytes": 28351488,
      "activation_bytes_per_sample": 786432,
      "forward_time_s": 0.013787432748358697,
      "backward_time_s": 0.03559912400669418
    },
    {
      "index": 4,
      "param_bytes": 28351488,
      "activation_bytes_per_sample": 786432,
      "forward_time_s": 0.02991512749576941,
      "backward_time_s": 0.05754325425368734
    },
    {
      "index": 5,
      "param_bytes": 28351488,
      "activation_bytes_per_sample": 786432,
      "forward_time_s": 0.012924363749334589,
      "backward_time_s": 0.036354180992930196
    },
    {
      "index": 6,
      "param_bytes": 28351488,
      "activation_bytes_per_sample": 786432,
      "forward_time_s": 0.022701051013427787,
      "backward_time_s": 0.036178209993522614
    },
    {
      "index": 7,
      "param_bytes": 28351488,
      "activation_bytes_per_sample": 786432,
      "forward_time_s": 0.023719409029581584,
      "backward_time_s": 0.057704209990333766
    },
    {
      "index": 8,
      "param_bytes": 28351488,
      "activation_bytes_per_sample": 786432,
      "forward_time_s": 0.022699600725900382,
      "backward_time_s": 0.036045022250618786
    },
    {
      "index": 9,
      "param_bytes": 28351488,
      "activation_bytes_per_sample": 786432,
      "forward_time_s": 0.022620921256020665,
      "backward_time_s": 0.046641741995699704
    },
    {
      "index": 10,
      "param_bytes": 28351488,
      "activation_bytes_per_sample": 786432,
      "forward_time_s": 0.02360594752826728,
      "backward_time_s": 0.04330297250999138
    },
    {
      "index": 11,
      "param_bytes": 28351488,
      "activation_bytes_per_sample": 786432,
      "forward_time_s": 0.022844826482469216,
      "backward_time_s": 0.036250007746275514
    }
  ],
  "head&tail": [
    {
      "index": "embed",
      "forward_time_s": 0.0006045777554390952,
      "backward_time_s": 8.118266123346984e-06
    },
    {
      "index": "lm_head",
      "forward_time_s": 0.056497507757740095,
      "backward_time_s": 0.12132047649356537
    }
  ]
}