{
  "host": "CPU50",
  "dtype": "float32",
  "seq_len": 256,
  "batch": 2,
  "vocab_size": 151936,
  "hidden": 2048,
  "embed_param_bytes": 1244659712,
  "tail_param_bytes": 1244667904,
  "layers": [
    {
      "index": 0,
      "param_bytes": 201344000,
      "activation_bytes_per_sample": 2097152,
      "forward_time_s": 0.1183664850104833,
      "backward_time_s": 0.20711064273200464
    },
    {
      "index": 1,
      "param_bytes": 201344000,
      "activation_bytes_per_sample": 2097152,
      "forward_time_s": 0.1245961472595809,
      "backward_time_s": 0.20752083501429297
    },
    {
      "index": 2,
      "param_bytes": 201344000,
      "activation_bytes_per_sample": 2097152,
      "forward_time_s": 0.12922568526118994,
      "backward_time_s": 0.205075469246367
    },
    {
      "index": 3,
      "param_bytes": 201344000,
      "activation_bytes_per_sample": 2097152,
      "forward_time_s": 0.1274015880189836,
      "backward_time_s": 0.20446535474911798
    },
    {
      "index": 4,
      "param_bytes": 201344000,
      "activation_bytes_per_sample": 2097152,
      "forward_time_s": 0.11634328549553175,
      "backward_time_s": 0.20294645725516602
    },
    {
      "index": 5,
      "param_bytes": 201344000,
      "activation_bytes_per_sample": 2097152,
      "forward_time_s": 0.12037278675416019,
      "backward_time_s": 0.1972350962460041
    },
    {
      "index": 6,
      "param_bytes": 201344000,
      "activation_bytes_per_sample": 2097152,
      "forward_time_s": 0.12900536798406392,
      "backward_time_s": 0.18589580050320365
    },
    {
      "index": 7,
      "param_bytes": 201344000,
      "activation_bytes_per_sample": 2097152,
      "forward_time_s": 0.12856228573946282,
      "backward_time_s": 0.18559992751397658
    },
    {
      "index": 8,
      "param_bytes": 201344000,
      "activation_bytes_per_sample": 2097152,
      "forward_time_s": 0.12739951771800406,
      "backward_time_s": 0.19049942327546887
    },
    {
      "index": 9,
      "param_bytes": 201344000,
      "activation_bytes_per_sample": 2097152,
      "forward_time_s": 0.11753014002169948,
      "backward_time_s": 0.1854459087480791
    },
    {
      "index": 10,
      "param_bytes": 201344000,
      "activation_bytes_per_sample": 2097152,
      "forward_time_s": 0.10376700975757558,
      "backward_time_s": 0.1882881530036684
    },
    {
      "index": 11,
      "param_bytes": 201344000,
      "activation_bytes_per_sample": 2097152,
      "forward_time_s": 0.1026494734978769,
      "backward_time_s": 0.18379707500571385
    },
    {
      "index": 12,
      "param_bytes": 201344000,
      "activation_bytes_per_sample": 2097152,
      "forward_time_s": 0.09864721697522327,
      "backward_time_s": 0.1915003672329476
    },
    {
      "index": 13,
      "param_bytes": 201344000,
      "activation_bytes_per_sample": 2097152,
      "forward_time_s": 0.0996974402514752,
      "backward_time_s": 0.19442603923380375
    },
    {
      "index": 14,
      "param_bytes": 201344000,
      "activation_bytes_per_sample": 2097152,
      "forward_time_s": 0.10374026624776889,
      "backward_time_s": 0.19080463299178518
    },
    {
      "index": 15,
      "param_bytes": 201344000,
      "activation_bytes_per_sample": 2097152,
      "forward_time_s": 0.1051643517712364,
      "backward_time_s": 0.1908422279957449
    },
    {
      "index": 16,
      "param_bytes": 201344000,
      "activation_bytes_per_sample": 2097152,
      "forward_time_s": 0.10605752174160443,
      "backward_time_s": 0.18754989551962353
    },
    {
      "index": 17,
      "param_bytes": 201344000,
      "activation_bytes_per_sample": 2097152,
      "forward_time_s": 0.10906371021701489,
      "backward_time_s": 0.17783103325928096
    },
    {
      "index": 18,
      "param_bytes": 201344000,
      "activation_bytes_per_sample": 2097152,
      "forward_time_s": 0.11097591524594463,
      "backward_time_s": 0.1780189257551683
    },
    {
      "index": 19,
      "param_bytes": 201344000,
      "activation_bytes_per_sample": 2097152,
      "forward_time_s": 0.10986738200881518,
      "backward_time_s": 0.1751718637533486
    },
    {
      "index": 20,
      "param_bytes": 201344000,
      "activation_bytes_per_sample": 2097152,
      "forward_time_s": 0.11864875575702172,
      "backward_time_s": 0.16533546800201293
    },
    {
      "index": 21,
      "param_bytes": 201344000,
      "activation_bytes_per_sample": 2097152,
      "forward_time_s": 0.11673454201081768,
      "backward_time_s": 0.16573828924447298
    },
    {
      "index": 22,
      "param_bytes": 201344000,
      "activation_bytes_per_sample": 2097152,
      "forward_time_s": 0.11721392851904966,
      "backward_time_s": 0.163591489996179
    },
    {
      "index": 23,
      "param_bytes": 201344000,
      "activation_bytes_per_sample": 2097152,
      "forward_time_s": 0.12376856549235526,
      "backward_time_s": 0.1543187597708311
    },
    {
      "index": 24,
      "param_bytes": 201344000,
      "activation_bytes_per_sample": 2097152,
      "forward_time_s": 0.12197140099306125,
      "backward_time_s": 0.1517662987462245
    },
    {
      "index": 25,
      "param_bytes": 201344000,
      "activation_bytes_per_sample": 2097152,
      "forward_time_s": 0.1236812067363644,
      "backward_time_s": 0.15054920873080846
    },
    {
      "index": 26,
      "param_bytes": 201344000,
      "activation_bytes_per_sample": 2097152,
      "forward_time_s": 0.12232411849254277,
      "backward_time_s": 0.15113970373931807
    },
    {
      "index": 27,
      "param_bytes": 201344000,
      "activation_bytes_per_sample": 2097152,
      "forward_time_s": 0.12296942125249188,
      "backward_time_s": 0.15360371199494693
    }
  ],
  "head&tail": [
    {
      "index": "embed",
      "forward_time_s": 0.0007475499878637493,
      "backward_time_s": 5.259498720988631e-06
    },
    {
      "index": "lm_head",
      "forward_time_s": 0.5642234290135093,
      "backward_time_s": 0.7297824730194407
    }
  ]
}