{
  "host": "CPU50",
  "dtype": "float32",
  "seq_len": 256,
  "batch": 8,
  "vocab_size": 151936,
  "hidden": 2048,
  "embed_param_bytes": 1244659712,
  "tail_param_bytes": 1244667904,
  "layers": [
    {
      "index": 0,
      "param_bytes": 201344000,
      "activation_bytes_per_sample": 2097152,
      "forward_time_s": 0.006412503224855755,
      "backward_time_s": 0.019509489501701872
    },
    {
      "index": 1,
      "param_bytes": 201344000,
      "activation_bytes_per_sample": 2097152,
      "forward_time_s": 0.006356723064964172,
      "backward_time_s": 0.019522649113523537
    },
    {
      "index": 2,
      "param_bytes": 201344000,
      "activation_bytes_per_sample": 2097152,
      "forward_time_s": 0.006134030204848387,
      "backward_time_s": 0.01967699006902231
    },
    {
      "index": 3,
      "param_bytes": 201344000,
      "activation_bytes_per_sample": 2097152,
      "forward_time_s": 0.005778449874778744,
      "backward_time_s": 0.0199530486082727
    },
    {
      "index": 4,
      "param_bytes": 201344000,
      "activation_bytes_per_sample": 2097152,
      "forward_time_s": 0.005787091330275871,
      "backward_time_s": 0.019872117135529974
    },
    {
      "index": 5,
      "param_bytes": 201344000,
      "activation_bytes_per_sample": 2097152,
      "forward_time_s": 0.0058873809999204245,
      "backward_time_s": 0.019675170952334065
    },
    {
      "index": 6,
      "param_bytes": 201344000,
      "activation_bytes_per_sample": 2097152,
      "forward_time_s": 0.00581367970968131,
      "backward_time_s": 0.01941701100750719
    },
    {
      "index": 7,
      "param_bytes": 201344000,
      "activation_bytes_per_sample": 2097152,
      "forward_time_s": 0.0056868082299479285,
      "backward_time_s": 0.019254587172155894
    },
    {
      "index": 8,
      "param_bytes": 201344000,
      "activation_bytes_per_sample": 2097152,
      "forward_time_s": 0.005973720900074113,
      "backward_time_s": 0.018981304031423757
    },
    {
      "index": 9,
      "param_bytes": 201344000,
      "activation_bytes_per_sample": 2097152,
      "forward_time_s": 0.005707787180144806,
      "backward_time_s": 0.018471024274668645
    },
    {
      "index": 10,
      "param_bytes": 201344000,
      "activation_bytes_per_sample": 2097152,
      "forward_time_s": 0.005732321455143392,
      "backward_time_s": 0.017989208072859596
    },
    {
      "index": 11,
      "param_bytes": 201344000,
      "activation_bytes_per_sample": 2097152,
      "forward_time_s": 0.00572869987518061,
      "backward_time_s": 0.017792835801522695
    },
    {
      "index": 12,
      "param_bytes": 201344000,
      "activation_bytes_per_sample": 2097152,
      "forward_time_s": 0.005855514949653298,
      "backward_time_s": 0.017447658895589545
    },
    {
      "index": 13,
      "param_bytes": 201344000,
      "activation_bytes_per_sample": 2097152,
      "forward_time_s": 0.0057113815800403245,
      "backward_time_s": 0.018134052791431005
    },
    {
      "index": 14,
      "param_bytes": 201344000,
      "activation_bytes_per_sample": 2097152,
      "forward_time_s": 0.005621645659848582,
      "backward_time_s": 0.01752797104373551
    },
    {
      "index": 15,
      "param_bytes": 201344000,
      "activation_bytes_per_sample": 2097152,
      "forward_time_s": 0.005599967275047675,
      "backward_time_s": 0.01725721045704896
    },
    {
      "index": 16,
      "param_bytes": 201344000,
      "activation_bytes_per_sample": 2097152,
      "forward_time_s": 0.0056831375951878725,
      "backward_time_s": 0.01748670267174596
    },
    {
      "index": 17,
      "param_bytes": 201344000,
      "activation_bytes_per_sample": 2097152,
      "forward_time_s": 0.005787161870102864,
      "backward_time_s": 0.01682346992953387
    },
    {
      "index": 18,
      "param_bytes": 201344000,
      "activation_bytes_per_sample": 2097152,
      "forward_time_s": 0.00573230876994785,
      "backward_time_s": 0.0166233693434709
    },
    {
      "index": 19,
      "param_bytes": 201344000,
      "activation_bytes_per_sample": 2097152,
      "forward_time_s": 0.005716085614985786,
      "backward_time_s": 0.016509429069123775
    },
    {
      "index": 20,
      "param_bytes": 201344000,
      "activation_bytes_per_sample": 2097152,
      "forward_time_s": 0.005732211074791849,
      "backward_time_s": 0.016650539690516875
    },
    {
      "index": 21,
      "param_bytes": 201344000,
      "activation_bytes_per_sample": 2097152,
      "forward_time_s": 0.005725339119962882,
      "backward_time_s": 0.01654348868266062
    },
    {
      "index": 22,
      "param_bytes": 201344000,
      "activation_bytes_per_sample": 2097152,
      "forward_time_s": 0.005697967625164893,
      "backward_time_s": 0.017004202321317458
    },
    {
      "index": 23,
      "param_bytes": 201344000,
      "activation_bytes_per_sample": 2097152,
      "forward_time_s": 0.005698393940110691,
      "backward_time_s": 0.01663061915939801
    },
    {
      "index": 24,
      "param_bytes": 201344000,
      "activation_bytes_per_sample": 2097152,
      "forward_time_s": 0.005768762955267448,
      "backward_time_s": 0.016277211412994257
    },
    {
      "index": 25,
      "param_bytes": 201344000,
      "activation_bytes_per_sample": 2097152,
      "forward_time_s": 0.00575403389550047,
      "backward_time_s": 0.016341955399407807
    },
    {
      "index": 26,
      "param_bytes": 201344000,
      "activation_bytes_per_sample": 2097152,
      "forward_time_s": 0.005707400055252947,
      "backward_time_s": 0.016309903812422852
    },
    {
      "index": 27,
      "param_bytes": 201344000,
      "activation_bytes_per_sample": 2097152,
      "forward_time_s": 0.005768700254848227,
      "backward_time_s": 0.01641337263596666
    }
  ],
  "head&tail": [
    {
      "index": "embed",
      "forward_time_s": 3.2480355293955654e-05,
      "backward_time_s": 1.1462908270250718e-07
    },
    {
      "index": "lm_head",
      "forward_time_s": 0.027300276620371735,
      "backward_time_s": 0.08355838308288334
    }
  ]
}