{
  "host": "CPU50",
  "dtype": "float32",
  "seq_len": 256,
  "batch": 6,
  "vocab_size": 151936,
  "hidden": 2048,
  "embed_param_bytes": 1244659712,
  "tail_param_bytes": 1244667904,
  "layers": [
    {
      "index": 0,
      "param_bytes": 201344000,
      "activation_bytes_per_sample": 2097152,
      "forward_time_s": 0.003069548286051334,
      "backward_time_s": 0.008157613959770719
    },
    {
      "index": 1,
      "param_bytes": 201344000,
      "activation_bytes_per_sample": 2097152,
      "forward_time_s": 0.0033912109861072774,
      "backward_time_s": 0.008166207426426672
    },
    {
      "index": 2,
      "param_bytes": 201344000,
      "activation_bytes_per_sample": 2097152,
      "forward_time_s": 0.003107906047241866,
      "backward_time_s": 0.00839719950490808
    },
    {
      "index": 3,
      "param_bytes": 201344000,
      "activation_bytes_per_sample": 2097152,
      "forward_time_s": 0.003164713208550691,
      "backward_time_s": 0.008072574117389361
    },
    {
      "index": 4,
      "param_bytes": 201344000,
      "activation_bytes_per_sample": 2097152,
      "forward_time_s": 0.002962948535989401,
      "backward_time_s": 0.007995670776145294
    },
    {
      "index": 5,
      "param_bytes": 201344000,
      "activation_bytes_per_sample": 2097152,
      "forward_time_s": 0.0029631962611650427,
      "backward_time_s": 0.007753256882195656
    },
    {
      "index": 6,
      "param_bytes": 201344000,
      "activation_bytes_per_sample": 2097152,
      "forward_time_s": 0.002967634166674947,
      "backward_time_s": 0.007689803611704923
    },
    {
      "index": 7,
      "param_bytes": 201344000,
      "activation_bytes_per_sample": 2097152,
      "forward_time_s": 0.0031237366415249805,
      "backward_time_s": 0.007797594736763218
    },
    {
      "index": 8,
      "param_bytes": 201344000,
      "activation_bytes_per_sample": 2097152,
      "forward_time_s": 0.0029470618028426543,
      "backward_time_s": 0.007972076263050557
    },
    {
      "index": 9,
      "param_bytes": 201344000,
      "activation_bytes_per_sample": 2097152,
      "forward_time_s": 0.0028883653694518016,
      "backward_time_s": 0.007853872559514386
    },
    {
      "index": 10,
      "param_bytes": 201344000,
      "activation_bytes_per_sample": 2097152,
      "forward_time_s": 0.0026850982249015942,
      "backward_time_s": 0.007929586708168308
    },
    {
      "index": 11,
      "param_bytes": 201344000,
      "activation_bytes_per_sample": 2097152,
      "forward_time_s": 0.0026812936640150534,
      "backward_time_s": 0.007907351021282816
    },
    {
      "index": 12,
      "param_bytes": 201344000,
      "activation_bytes_per_sample": 2097152,
      "forward_time_s": 0.0026897545695343675,
      "backward_time_s": 0.0076196067265530305
    },
    {
      "index": 13,
      "param_bytes": 201344000,
      "activation_bytes_per_sample": 2097152,
      "forward_time_s": 0.0027275576555338276,
      "backward_time_s": 0.007569957576204515
    },
    {
      "index": 14,
      "param_bytes": 201344000,
      "activation_bytes_per_sample": 2097152,
      "forward_time_s": 0.0027779019777275002,
      "backward_time_s": 0.0076511616000998674
    },
    {
      "index": 15,
      "param_bytes": 201344000,
      "activation_bytes_per_sample": 2097152,
      "forward_time_s": 0.0026546825303941863,
      "backward_time_s": 0.007475179962875188
    },
    {
      "index": 16,
      "param_bytes": 201344000,
      "activation_bytes_per_sample": 2097152,
      "forward_time_s": 0.002688182622336576,
      "backward_time_s": 0.00770107225762679
    },
    {
      "index": 17,
      "param_bytes": 201344000,
      "activation_bytes_per_sample": 2097152,
      "forward_time_s": 0.0028059394666342997,
      "backward_time_s": 0.00739309627362428
    },
    {
      "index": 18,
      "param_bytes": 201344000,
      "activation_bytes_per_sample": 2097152,
      "forward_time_s": 0.0027762399669477925,
      "backward_time_s": 0.007360222188525339
    },
    {
      "index": 19,
      "param_bytes": 201344000,
      "activation_bytes_per_sample": 2097152,
      "forward_time_s": 0.0028524020746570184,
      "backward_time_s": 0.007048812873096416
    },
    {
      "index": 20,
      "param_bytes": 201344000,
      "activation_bytes_per_sample": 2097152,
      "forward_time_s": 0.002842785619496782,
      "backward_time_s": 0.00673428770289111
    },
    {
      "index": 21,
      "param_bytes": 201344000,
      "activation_bytes_per_sample": 2097152,
      "forward_time_s": 0.0028468376888971156,
      "backward_time_s": 0.0067744622171139295
    },
    {
      "index": 22,
      "param_bytes": 201344000,
      "activation_bytes_per_sample": 2097152,
      "forward_time_s": 0.002812964363935559,
      "backward_time_s": 0.006929592725034382
    },
    {
      "index": 23,
      "param_bytes": 201344000,
      "activation_bytes_per_sample": 2097152,
      "forward_time_s": 0.0028585614056080683,
      "backward_time_s": 0.006846463084977763
    },
    {
      "index": 24,
      "param_bytes": 201344000,
      "activation_bytes_per_sample": 2097152,
      "forward_time_s": 0.002827670902964504,
      "backward_time_s": 0.0067008220238765305
    },
    {
      "index": 25,
      "param_bytes": 201344000,
      "activation_bytes_per_sample": 2097152,
      "forward_time_s": 0.0028461956472407715,
      "backward_time_s": 0.006705995893126163
    },
    {
      "index": 26,
      "param_bytes": 201344000,
      "activation_bytes_per_sample": 2097152,
      "forward_time_s": 0.0028218499000003147,
      "backward_time_s": 0.006896535883861732
    },
    {
      "index": 27,
      "param_bytes": 201344000,
      "activation_bytes_per_sample": 2097152,
      "forward_time_s": 0.0028746911444209725,
      "backward_time_s": 0.00678431295688703
    }
  ],
  "head&tail": [
    {
      "index": "embed",
      "forward_time_s": 2.0159727783821938e-05,
      "backward_time_s": 1.1244171838637861e-07
    },
    {
      "index": "lm_head",
      "forward_time_s": 0.0131491962585844,
      "backward_time_s": 0.032300342128164294
    }
  ]
}