{
  "host": "CPU50",
  "dtype": "float32",
  "seq_len": 256,
  "batch": 7,
  "vocab_size": 151936,
  "hidden": 2048,
  "embed_param_bytes": 1244659712,
  "tail_param_bytes": 1244667904,
  "layers": [
    {
      "index": 0,
      "param_bytes": 201344000,
      "activation_bytes_per_sample": 2097152,
      "forward_time_s": 0.0159782664866523,
      "backward_time_s": 0.050044432392881325
    },
    {
      "index": 1,
      "param_bytes": 201344000,
      "activation_bytes_per_sample": 2097152,
      "forward_time_s": 0.017483877042347253,
      "backward_time_s": 0.04983359286695049
    },
    {
      "index": 2,
      "param_bytes": 201344000,
      "activation_bytes_per_sample": 2097152,
      "forward_time_s": 0.01614809312579584,
      "backward_time_s": 0.04953365891333485
    },
    {
      "index": 3,
      "param_bytes": 201344000,
      "activation_bytes_per_sample": 2097152,
      "forward_time_s": 0.015463283084197125,
      "backward_time_s": 0.050136530277201455
    },
    {
      "index": 4,
      "param_bytes": 201344000,
      "activation_bytes_per_sample": 2097152,
      "forward_time_s": 0.015234880319945255,
      "backward_time_s": 0.04948220527597442
    },
    {
      "index": 5,
      "param_bytes": 201344000,
      "activation_bytes_per_sample": 2097152,
      "forward_time_s": 0.015402671680527015,
      "backward_time_s": 0.049865026479741566
    },
    {
      "index": 6,
      "param_bytes": 201344000,
      "activation_bytes_per_sample": 2097152,
      "forward_time_s": 0.014686494360729637,
      "backward_time_s": 0.04983951681819947
    },
    {
      "index": 7,
      "param_bytes": 201344000,
      "activation_bytes_per_sample": 2097152,
      "forward_time_s": 0.014458817277045455,
      "backward_time_s": 0.04974982915091855
    },
    {
      "index": 8,
      "param_bytes": 201344000,
      "activation_bytes_per_sample": 2097152,
      "forward_time_s": 0.015134859292528642,
      "backward_time_s": 0.046895840454877914
    },
    {
      "index": 9,
      "param_bytes": 201344000,
      "activation_bytes_per_sample": 2097152,
      "forward_time_s": 0.014625916180698873,
      "backward_time_s": 0.04742561754970278
    },
    {
      "index": 10,
      "param_bytes": 201344000,
      "activation_bytes_per_sample": 2097152,
      "forward_time_s": 0.015208786583874218,
      "backward_time_s": 0.04943040650284558
    },
    {
      "index": 11,
      "param_bytes": 201344000,
      "activation_bytes_per_sample": 2097152,
      "forward_time_s": 0.014949798388341958,
      "backward_time_s": 0.05042446632510633
    },
    {
      "index": 12,
      "param_bytes": 201344000,
      "activation_bytes_per_sample": 2097152,
      "forward_time_s": 0.014944776737441618,
      "backward_time_s": 0.048975862290943965
    },
    {
      "index": 13,
      "param_bytes": 201344000,
      "activation_bytes_per_sample": 2097152,
      "forward_time_s": 0.014884486666738262,
      "backward_time_s": 0.04941591029787039
    },
    {
      "index": 14,
      "param_bytes": 201344000,
      "activation_bytes_per_sample": 2097152,
      "forward_time_s": 0.015017505209673092,
      "backward_time_s": 0.04947958513979318
    },
    {
      "index": 15,
      "param_bytes": 201344000,
      "activation_bytes_per_sample": 2097152,
      "forward_time_s": 0.014874175569275394,
      "backward_time_s": 0.04865843938661761
    },
    {
      "index": 16,
      "param_bytes": 201344000,
      "activation_bytes_per_sample": 2097152,
      "forward_time_s": 0.015310716194411118,
      "backward_time_s": 0.0477684082602806
    },
    {
      "index": 17,
      "param_bytes": 201344000,
      "activation_bytes_per_sample": 2097152,
      "forward_time_s": 0.015430459152816586,
      "backward_time_s": 0.046020330218855925
    },
    {
      "index": 18,
      "param_bytes": 201344000,
      "activation_bytes_per_sample": 2097152,
      "forward_time_s": 0.01518437456899038,
      "backward_time_s": 0.04698049071269743
    },
    {
      "index": 19,
      "param_bytes": 201344000,
      "activation_bytes_per_sample": 2097152,
      "forward_time_s": 0.015307410583773162,
      "backward_time_s": 0.047338785316745416
    },
    {
      "index": 20,
      "param_bytes": 201344000,
      "activation_bytes_per_sample": 2097152,
      "forward_time_s": 0.01563651670827918,
      "backward_time_s": 0.04641706857755744
    },
    {
      "index": 21,
      "param_bytes": 201344000,
      "activation_bytes_per_sample": 2097152,
      "forward_time_s": 0.015051380584837817,
      "backward_time_s": 0.046199067667625444
    },
    {
      "index": 22,
      "param_bytes": 201344000,
      "activation_bytes_per_sample": 2097152,
      "forward_time_s": 0.015473293777581096,
      "backward_time_s": 0.043502936818178656
    },
    {
      "index": 23,
      "param_bytes": 201344000,
      "activation_bytes_per_sample": 2097152,
      "forward_time_s": 0.01576716441761366,
      "backward_time_s": 0.043538984821432015
    },
    {
      "index": 24,
      "param_bytes": 201344000,
      "activation_bytes_per_sample": 2097152,
      "forward_time_s": 0.015488425500128262,
      "backward_time_s": 0.043622813081247325
    },
    {
      "index": 25,
      "param_bytes": 201344000,
      "activation_bytes_per_sample": 2097152,
      "forward_time_s": 0.01564244915385239,
      "backward_time_s": 0.04383462195569031
    },
    {
      "index": 26,
      "param_bytes": 201344000,
      "activation_bytes_per_sample": 2097152,
      "forward_time_s": 0.01556309549939922,
      "backward_time_s": 0.04408135066998813
    },
    {
      "index": 27,
      "param_bytes": 201344000,
      "activation_bytes_per_sample": 2097152,
      "forward_time_s": 0.0157602692917054,
      "backward_time_s": 0.0431903890516285
    }
  ],
  "head&tail": [
    {
      "index": "embed",
      "forward_time_s": 9.201952828637634e-05,
      "backward_time_s": 5.682413613519415e-07
    },
    {
      "index": "lm_head",
      "forward_time_s": 0.0776589956949465,
      "backward_time_s": 0.19199558288588744
    }
  ]
}