{
  "host": "CPU50",
  "dtype": "float32",
  "seq_len": 256,
  "batch": 1,
  "vocab_size": 151936,
  "hidden": 1024,
  "embed_param_bytes": 622329856,
  "tail_param_bytes": 622333952,
  "layers": [
    {
      "index": 0,
      "param_bytes": 62923776,
      "activation_bytes_per_sample": 1048576,
      "forward_time_s": 0.0005495933053316548,
      "backward_time_s": 0.002769497054294041
    },
    {
      "index": 1,
      "param_bytes": 62923776,
      "activation_bytes_per_sample": 1048576,
      "forward_time_s": 0.0005109511950286105,
      "backward_time_s": 0.0027601146290478946
    },
    {
      "index": 2,
      "param_bytes": 62923776,
      "activation_bytes_per_sample": 1048576,
      "forward_time_s": 0.0004612084649852477,
      "backward_time_s": 0.0027522209487922567
    },
    {
      "index": 3,
      "param_bytes": 62923776,
      "activation_bytes_per_sample": 1048576,
      "forward_time_s": 0.0004562730246107094,
      "backward_time_s": 0.0028449073649100673
    },
    {
      "index": 4,
      "param_bytes": 62923776,
      "activation_bytes_per_sample": 1048576,
      "forward_time_s": 0.0004655864054802805,
      "backward_time_s": 0.0027156227187021226
    },
    {
      "index": 5,
      "param_bytes": 62923776,
      "activation_bytes_per_sample": 1048576,
      "forward_time_s": 0.0004445108704385348,
      "backward_time_s": 0.0027650960278313283
    },
    {
      "index": 6,
      "param_bytes": 62923776,
      "activation_bytes_per_sample": 1048576,
      "forward_time_s": 0.0004708040549303405,
      "backward_time_s": 0.002764943496334462
    },
    {
      "index": 7,
      "param_bytes": 62923776,
      "activation_bytes_per_sample": 1048576,
      "forward_time_s": 0.000499409685144201,
      "backward_time_s": 0.0028133174404725617
    },
    {
      "index": 8,
      "param_bytes": 62923776,
      "activation_bytes_per_sample": 1048576,
      "forward_time_s": 0.00044905228016432373,
      "backward_time_s": 0.0027753453774698807
    },
    {
      "index": 9,
      "param_bytes": 62923776,
      "activation_bytes_per_sample": 1048576,
      "forward_time_s": 0.00045185957016656174,
      "backward_time_s": 0.0027589600694531385
    },
    {
      "index": 10,
      "param_bytes": 62923776,
      "activation_bytes_per_sample": 1048576,
      "forward_time_s": 0.0005555000450112857,
      "backward_time_s": 0.002134067694676548
    },
    {
      "index": 11,
      "param_bytes": 62923776,
      "activation_bytes_per_sample": 1048576,
      "forward_time_s": 0.0006497783301165328,
      "backward_time_s": 0.0018263208240196132
    },
    {
      "index": 12,
      "param_bytes": 62923776,
      "activation_bytes_per_sample": 1048576,
      "forward_time_s": 0.0005829058642848395,
      "backward_time_s": 0.001960601418841656
    },
    {
      "index": 13,
      "param_bytes": 62923776,
      "activation_bytes_per_sample": 1048576,
      "forward_time_s": 0.0005612235801527276,
      "backward_time_s": 0.001959643401560065
    },
    {
      "index": 14,
      "param_bytes": 62923776,
      "activation_bytes_per_sample": 1048576,
      "forward_time_s": 0.0005883069799165241,
      "backward_time_s": 0.0019309069536959389
    },
    {
      "index": 15,
      "param_bytes": 62923776,
      "activation_bytes_per_sample": 1048576,
      "forward_time_s": 0.0006129515657084994,
      "backward_time_s": 0.0018817386654480758
    },
    {
      "index": 16,
      "param_bytes": 62923776,
      "activation_bytes_per_sample": 1048576,
      "forward_time_s": 0.0006336448196088895,
      "backward_time_s": 0.001960727999841699
    },
    {
      "index": 17,
      "param_bytes": 62923776,
      "activation_bytes_per_sample": 1048576,
      "forward_time_s": 0.0006336247353465296,
      "backward_time_s": 0.001791788716628672
    },
    {
      "index": 18,
      "param_bytes": 62923776,
      "activation_bytes_per_sample": 1048576,
      "forward_time_s": 0.0005939926998689771,
      "backward_time_s": 0.0018414867113600015
    },
    {
      "index": 19,
      "param_bytes": 62923776,
      "activation_bytes_per_sample": 1048576,
      "forward_time_s": 0.0006136607099324465,
      "backward_time_s": 0.0017827349116259703
    },
    {
      "index": 20,
      "param_bytes": 62923776,
      "activation_bytes_per_sample": 1048576,
      "forward_time_s": 0.0005938230999163352,
      "backward_time_s": 0.0020458286438106562
    },
    {
      "index": 21,
      "param_bytes": 62923776,
      "activation_bytes_per_sample": 1048576,
      "forward_time_s": 0.000586950764991343,
      "backward_time_s": 0.0019269624103778582
    },
    {
      "index": 22,
      "param_bytes": 62923776,
      "activation_bytes_per_sample": 1048576,
      "forward_time_s": 0.0006588736746925861,
      "backward_time_s": 0.0015720552338069386
    },
    {
      "index": 23,
      "param_bytes": 62923776,
      "activation_bytes_per_sample": 1048576,
      "forward_time_s": 0.0006398667700705118,
      "backward_time_s": 0.0013913408210659162
    },
    {
      "index": 24,
      "param_bytes": 62923776,
      "activation_bytes_per_sample": 1048576,
      "forward_time_s": 0.0006072125854552724,
      "backward_time_s": 0.0016754764871952626
    },
    {
      "index": 25,
      "param_bytes": 62923776,
      "activation_bytes_per_sample": 1048576,
      "forward_time_s": 0.0006921927598887123,
      "backward_time_s": 0.001387102057852221
    },
    {
      "index": 26,
      "param_bytes": 62923776,
      "activation_bytes_per_sample": 1048576,
      "forward_time_s": 0.0006959874596213922,
      "backward_time_s": 0.0014253423026599223
    },
    {
      "index": 27,
      "param_bytes": 62923776,
      "activation_bytes_per_sample": 1048576,
      "forward_time_s": 0.0007173853949643672,
      "backward_time_s": 0.001527643116332805
    }
  ],
  "head&tail": [
    {
      "index": "embed",
      "forward_time_s": 1.2613165017683059e-05,
      "backward_time_s": 3.0031187391829445e-07
    },
    {
      "index": "lm_head",
      "forward_time_s": 0.005519604030123446,
      "backward_time_s": 0.007898646300665033
    }
  ]
}