{
  "host": "CPU30",
  "dtype": "float32",
  "seq_len": 256,
  "batch": 7,
  "vocab_size": 30522,
  "hidden": 768,
  "embed_param_bytes": 93763584,
  "tail_param_bytes": 0,
  "layers": [
    {
      "index": 0,
      "param_bytes": 28351488,
      "activation_bytes_per_sample": 786432,
      "forward_time_s": 0.0369856456237085,
      "backward_time_s": 0.12373486689635471
    },
    {
      "index": 1,
      "param_bytes": 28351488,
      "activation_bytes_per_sample": 786432,
      "forward_time_s": 0.036724342135926485,
      "backward_time_s": 0.10696491136081335
    },
    {
      "index": 2,
      "param_bytes": 28351488,
      "activation_bytes_per_sample": 786432,
      "forward_time_s": 0.043141776248782106,
      "backward_time_s": 0.10975032366670379
    },
    {
      "index": 3,
      "param_bytes": 28351488,
      "activation_bytes_per_sample": 786432,
      "forward_time_s": 0.04334185635839147,
      "backward_time_s": 0.11483481523257327
    },
    {
      "index": 4,
      "param_bytes": 28351488,
      "activation_bytes_per_sample": 786432,
      "forward_time_s": 0.0434206574312075,
      "backward_time_s": 0.1089727367444072
    },
    {
      "index": 5,
      "param_bytes": 28351488,
      "activation_bytes_per_sample": 786432,
      "forward_time_s": 0.04763408862456834,
      "backward_time_s": 0.11844465715763276
    },
    {
      "index": 6,
      "param_bytes": 28351488,
      "activation_bytes_per_sample": 786432,
      "forward_time_s": 0.04314618347303359,
      "backward_time_s": 0.1258164614610654
    },
    {
      "index": 7,
      "param_bytes": 28351488,
      "activation_bytes_per_sample": 786432,
      "forward_time_s": 0.043477160390975926,
      "backward_time_s": 0.11017120053562057
    },
    {
      "index": 8,
      "param_bytes": 28351488,
      "activation_bytes_per_sample": 786432,
      "forward_time_s": 0.043034858755050004,
      "backward_time_s": 0.1221533412864163
    },
    {
      "index": 9,
      "param_bytes": 28351488,
      "activation_bytes_per_sample": 786432,
      "forward_time_s": 0.044927258979115446,
      "backward_time_s": 0.1108063088383929
    },
    {
      "index": 10,
      "param_bytes": 28351488,
      "activation_bytes_per_sample": 786432,
      "forward_time_s": 0.039390192772934304,
      "backward_time_s": 0.11773034581419234
    },
    {
      "index": 11,
      "param_bytes": 28351488,
      "activation_bytes_per_sample": 786432,
      "forward_time_s": 0.03581845174294935,
      "backward_time_s": 0.1032047066121762
    }
  ],
  "head&tail": [
    {
      "index": "embed",
      "forward_time_s": 0.0005110344710439867,
      "backward_time_s": 4.869695786577411e-06
    },
    {
      "index": "lm_head",
      "forward_time_s": 0.1165127224317921,
      "backward_time_s": 0.2601929892249261
    }
  ]
}